MANIFEST.in
README.rst
setup.py
pypuppetdb_daily_report/__init__.py
pypuppetdb_daily_report/pypuppetdb_daily_report.py
pypuppetdb_daily_report.egg-info/PKG-INFO
pypuppetdb_daily_report.egg-info/SOURCES.txt
pypuppetdb_daily_report.egg-info/dependency_links.txt
pypuppetdb_daily_report.egg-info/entry_points.txt
pypuppetdb_daily_report.egg-info/requires.txt
pypuppetdb_daily_report.egg-info/top_level.txt
pypuppetdb_daily_report/templates/base.html
pypuppetdb_daily_report/templates/facts.html
pypuppetdb_daily_report/templates/metrics.html
pypuppetdb_daily_report/templates/node_resources.html
pypuppetdb_daily_report/templates/nodes.html
pypuppetdb_daily_report/templates/report_resources.html
pypuppetdb_daily_report/templates/reports.html
pypuppetdb_daily_report/tests/__init__.py
pypuppetdb_daily_report/tests/pdr_test.py
pypuppetdb_daily_report/tests/test_data.py
pypuppetdb_daily_report/tests/test_templates.py