Metadata-Version: 1.1
Name: pypuppetdb-daily-report
Version: 0.0.2
Summary: Daily run summary report for PuppetDB, written in Python using nedap's pypuppetdb module.
Home-page: http://github.com/jantman/pypuppetdb-daily-report/
Author: Jason Antman
Author-email: jason@jasonantman.com
License: Apache 2
Keywords: puppet puppetdb report summary
Platform: UNKNOWN
Classifier: Development Status :: 4 - Beta
Classifier: Environment :: Console
Classifier: Intended Audience :: System Administrators
Classifier: Intended Audience :: Information Technology
Classifier: Natural Language :: English
Classifier: Operating System :: POSIX
Classifier: Programming Language :: Python
Classifier: Programming Language :: Python :: 3
